docrag/__init__.py
docrag/cli.py
docrag/config.py
docrag/convert.py
docrag/index.py
docrag/retrieve.py
docrag/utils.py
docrag_llm-0.1.27.dist-info/METADATA
docrag_llm-0.1.27.dist-info/WHEEL
docrag_llm-0.1.27.dist-info/entry_points.txt
docrag_llm-0.1.27.dist-info/licenses/LICENSE
docrag_llm-0.1.27.dist-info/RECORD
