Metadata-Version: 2.4
Name: docrag-llm
Version: 0.1.27
Summary: Docling → Chroma → Ollama: Simple RAG pipeline
Project-URL: Homepage, https://github.com/MadMando/docrag_llm
Project-URL: Repository, https://github.com/MadMando/docrag_llm
Project-URL: Issues, https://github.com/MadMando/docrag_llm/issues
Project-URL: HuggingFace, https://huggingface.co/MedinaArmando
Project-URL: LinkedIn, https://www.linkedin.com/in/medinaarmando0912
Author-email: Armando Medina <MedinaArmando0912@gmail.com>
License: MIT
License-File: LICENSE
Classifier: Development Status :: 3 - Alpha
Classifier: Intended Audience :: Developers
Classifier: License :: OSI Approved :: MIT License
Classifier: Operating System :: OS Independent
Classifier: Programming Language :: Python :: 3.10
Classifier: Programming Language :: Python :: 3.11
Classifier: Programming Language :: Python :: 3.12
Classifier: Typing :: Typed
Requires-Python: >=3.10
Requires-Dist: chromadb>=0.5.0
Requires-Dist: docling>=2.48.0
Requires-Dist: ollama>=0.3.0
Requires-Dist: pydantic>=2.7
Requires-Dist: typer>=0.12.0
Requires-Dist: watchdog>=4.0.0
Provides-Extra: dev
Requires-Dist: build>=1.2.1; extra == 'dev'
Requires-Dist: mypy>=1.10.0; extra == 'dev'
Requires-Dist: pytest>=8.0; extra == 'dev'
Requires-Dist: ruff>=0.5.0; extra == 'dev'
Requires-Dist: twine>=5.0.0; extra == 'dev'
